{
  "places": {
    "45073758f964a52021391fe3": {
      "name": "San Francisco Caltrain Station",
      "location": {
        "city": "San Francisco",
        "address": "700 4th St",
        "country": "USA",
        "lng": -122.394867539406,
        "crossStreet": "btw King St & Townsend St",
        "postalCode": "94107",
        "lat": 37.7766425825247,
        "state": "CA",
        "distance": 31
      },
      "hereNow": {
        "count": 0
      },
      "stats": {
        "checkinsCount": 24893,
        "usersCount": 5137
      },
      "contact": {
        "phone": "8006604287",
        "twitter": "caltrain"
      },
      "id": "45073758f964a52021391fe3",
      "verified": false,
      "categories": [
        {
          "name": "Train Station",
          "parents": [
            "Travel Spots"
          ],
          "primary": true,
          "id": "4bf58dd8d48988d129951735",
          "icon": "https://foursquare.com/img/categories/travel/trainstation.png",
          "pluralName": "Train Stations"
        },
        {
          "name": "Train",
          "parents": [
            "Travel Spots",
            "Train Stations"
          ],
          "id": "4bf58dd8d48988d12a951735",
          "icon": "https://foursquare.com/img/categories/travel/trainstation.png",
          "pluralName": "Trains"
        }
      ]
    },
    "4b2af448f964a520cbb224e3": {
      "name": "La Strada",
      "location": {
        "city": "Palo Alto",
        "address": "335 University Ave",
        "lng": -122.1613289,
        "postalCode": "94301",
        "lat": 37.4464164,
        "state": "CA",
        "distance": 8
      },
      "hereNow": {
        "count": 0
      },
      "stats": {
        "checkinsCount": 500,
        "usersCount": 365
      },
      "contact": {
      },
      "id": "4b2af448f964a520cbb224e3",
      "verified": false,
      "categories": [
        {
          "name": "Italian Restaurant",
          "parents": [
            "Food"
          ],
          "primary": true,
          "id": "4bf58dd8d48988d110941735",
          "icon": "https://foursquare.com/img/categories/food/default.png",
          "pluralName": "Italian Restaurants"
        }
      ]
    }
  },
  "blocks": {
    "4e4c659b6a9eba13ed000034": {
      "id": "4e4c659b6a9eba13ed000034",
      "end": 1313631198,
      "user_id": "4ce157547834d82432000211",
      "type": "section",
      "start": 1313629595,
      "count": 3,
      "state": "live",
      "moments": [
        "4e4c69206a9eba13ed000043",
        "4e4c6a236a9eba13ed000047",
        "4e4c6bc56a9eba13ed00004b"
      ],
      "active": false
    },
    "4e4c52d56a9eba13e7000007": {
      "id": "4e4c52d56a9eba13e7000007",
      "end": 1313627818,
      "user_id": "4ce157547834d82432000211",
      "type": "section",
      "start": 1313624789,
      "count": 6,
      "state": "live",
      "moments": [
        "4e4c52d56a9eba13e7000006",
        "4e4c53046a9eba13e7000009",
        "4e4c59ef6a9eba13ed000012",
        "4e4c5b056a9eba13ed000018",
        "4e4c5b3c6a9eba13ed00001b",
        "4e4c5cbc6a9eba13ed00001c"
      ],
      "active": false
    },
    "4e4c65776a9eba13ed000032": {
      "name": "Caltrain",
      "custom_id": "CB3E3CC8-CEEF-469A-BA50-0CF24A4DF4C1",
      "id": "4e4c65776a9eba13ed000032",
      "end": 1313629595,
      "user_id": "4ce157547834d82432000211",
      "type": "chapter",
      "start": 1313629559,
      "count": 1,
      "state": "live",
      "moments": [
        "4e4c65916a9eba13ed000033"
      ],
      "active": false
    },
    "4e4c6bde6a9eba13ed00004c": {
      "name": "dinner",
      "custom_id": "02576B62-D511-45B0-A269-486D3BAB41A1",
      "id": "4e4c6bde6a9eba13ed00004c",
      "end": 1313631483,
      "user_id": "4ce157547834d82432000211",
      "type": "chapter",
      "start": 1313631198,
      "count": 5,
      "state": "live",
      "moments": [
        "4e4c6bf66a9eba13ed00004d",
        "4e4c6c156a9eba13ed00004e",
        "4e4c6c9e6a9eba13ed00004f",
        "4e4c6caf6a9eba13ed000050",
        "4e4c6ce26a9eba13ed000051"
      ],
      "active": false
    },
    "4e4c6cfb6a9eba13ed000052": {
      "id": "4e4c6cfb6a9eba13ed000052",
      "user_id": "4ce157547834d82432000211",
      "type": "section",
      "start": 1313631483,
      "count": 1,
      "state": "live",
      "moments": [
        "4e4c6d076a9eba13ed000053"
      ],
      "active": true
    }
  },
  "seen_its": {
    "feed_views": {
      "most_recent": {
        "timestamp": 1313635330.24698,
        "user_id": "4c6b7734d6ea744abc000f34"
      },
      "total": 106,
      "users": [
        {
          "timestamp": 1313634984.27585,
          "user_id": "4ce157547834d82432000211",
          "count": 47
        },
        {
          "timestamp": 1313633425.7449,
          "user_id": "4c6b76fad6ea744abc000f20",
          "count": 22
        },
        {
          "timestamp": 1313635330.24698,
          "user_id": "4c6b7734d6ea744abc000f34",
          "count": 18
        },
        {
          "timestamp": 1313634666.52775,
          "user_id": "4c6b7705d6ea744abc000f23",
          "count": 9
        },
        {
          "timestamp": 1313624932.45725,
          "user_id": "4c932ff84914e5721e000007",
          "count": 5
        },
        {
          "timestamp": 1313633899.61329,
          "user_id": "4c6b76fed6ea744abc000f21",
          "count": 4
        },
        {
          "timestamp": 1313624815.48236,
          "user_id": "4cc7581122645d0edd000026",
          "count": 1
        }
      ]
    },
    "_id": "4e4c52455a3b2b2f708ae8b0",
    "user_id": "4ce157547834d82432000211"
  },
  "music": {
    "432163690": {
      "trackViewUrl": "http://itunes.apple.com/us/music-video/everybody-backstreets-back/id432163690?uo=4",
      "kind": "music-video",
      "collectionName": "NKOTBSB (Deluxe Version)",
      "collectionExplicitness": "notExplicit",
      "wrapperType": "track",
      "trackNumber": 4,
      "trackName": "Everybody (Backstreet's Back) [AC3 Stereo]",
      "trackExplicitness": "notExplicit",
      "shortDescription": null,
      "longDescription": null,
      "country": "USA",
      "artworkUrl100": "http://a2.mzstatic.com/us/r1000/052/Video/77/ab/2c/dj.pkehyekf.100x100-75.jpg",
      "artistId": 217039,
      "primaryGenreName": "Pop",
      "collectionViewUrl": "http://itunes.apple.com/us/music-video/everybody-backstreets-back/id432163690?uo=4",
      "artworkUrl60": "http://a5.mzstatic.com/us/r1000/052/Video/77/ab/2c/dj.pkehyekf.80x60-75.jpg",
      "contentAdvisoryRating": null,
      "collectionPrice": 14.99,
      "releaseDate": "2011-05-24T07:00:00Z",
      "id": "432163690",
      "trackCount": 24,
      "discCount": 2,
      "artworkUrl30": "http://a2.mzstatic.com/us/r1000/052/Video/77/ab/2c/dj.pkehyekf.40x30-75.jpg",
      "collectionId": 432163121,
      "collectionCensoredName": "NKOTBSB (Deluxe Version)",
      "artistViewUrl": "http://itunes.apple.com/us/artist/backstreet-boys/id217039?uo=4",
      "artistName": "Backstreet Boys",
      "trackTimeMillis": 303136.0,
      "currency": "USD",
      "trackCensoredName": "Everybody (Backstreet's Back) [AC3 Stereo]",
      "previewUrl": "http://a483.v.phobos.apple.com/us/r1000/013/Video/b0/5c/0c/mzi.edrkentu..640x336.h264lc.d2.p.m4v",
      "trackPrice": 0.99,
      "trackId": "432163690",
      "discNumber": 2
    },
    "336195090": {
      "trackViewUrl": "http://itunes.apple.com/us/music-video/in-the-air-tonight-live/id336195090?uo=4",
      "kind": "music-video",
      "collectionName": null,
      "collectionExplicitness": "notExplicit",
      "wrapperType": "track",
      "trackNumber": null,
      "trackName": "In the Air Tonight",
      "trackExplicitness": "notExplicit",
      "shortDescription": null,
      "longDescription": null,
      "country": "USA",
      "artworkUrl100": "http://a2.mzstatic.com/us/r1000/018/Video/6b/29/67/mzi.rjhyvecu.100x100-75.jpg",
      "artistId": 153718,
      "primaryGenreName": "Rock",
      "collectionViewUrl": null,
      "artworkUrl60": "http://a1.mzstatic.com/us/r1000/018/Video/6b/29/67/mzi.rjhyvecu.80x60-75.jpg",
      "contentAdvisoryRating": null,
      "collectionPrice": 1.99,
      "releaseDate": "1986-06-22T07:00:00Z",
      "id": "336195090",
      "trackCount": null,
      "discCount": null,
      "artworkUrl30": "http://a3.mzstatic.com/us/r1000/018/Video/6b/29/67/mzi.rjhyvecu.40x30-75.jpg",
      "collectionId": null,
      "collectionCensoredName": null,
      "artistViewUrl": "http://itunes.apple.com/us/artist/phil-collins/id153718?uo=4",
      "artistName": "Phil Collins",
      "trackTimeMillis": 314514.0,
      "currency": "USD",
      "trackCensoredName": "In the Air Tonight (Live)",
      "previewUrl": "http://a358.v.phobos.apple.com/us/r1000/018/Video/58/5b/c3/mzm.sctitnpi..640x480.h264lc.u.p.m4v",
      "trackPrice": 1.99,
      "trackId": "336195090",
      "discNumber": null
    }
  },
  "users": {
    "4cc7581122645d0edd000026": {
      "photo": {
        "ios": {
          "2x": {
            "height": 160,
            "file": "processed_160x160.jpg",
            "width": 160
          },
          "1x": {
            "height": 80,
            "file": "processed_80x80.jpg",
            "width": 80
          }
        },
        "url": "https://s3-us-west-1.amazonaws.com/images.path.com/profile_photos/5d22481e46ca527816c97528869d3bb4d714ca84",
        "version": 3,
        "original": {
          "file": "original.jpg"
        }
      },
      "facebook_id": "503474",
      "created_at": "2010-10-26 22:37:05",
      "username": "mallory",
      "id": "4cc7581122645d0edd000026",
      "gender": "male",
      "phone": "4088231500",
      "last_name": "Paine",
      "is_friend": true,
      "first_name": "Mallory",
      "email": "mpaine@gmail.com"
    },
    "4c6b7705d6ea744abc000f23": {
      "photo": {
        "ios": {
          "2x": {
            "height": 160,
            "file": "processed_160x160.jpg",
            "width": 160
          },
          "1x": {
            "height": 80,
            "file": "processed_80x80.jpg",
            "width": 80
          }
        },
        "url": "https://s3-us-west-1.amazonaws.com/images.path.com/profile_photos/b680d3f430ba03afc9d31024aea6a03607ec1fed",
        "version": 3,
        "original": {
          "file": "original.jpg"
        }
      },
      "facebook_id": "10200882",
      "created_at": "2010-04-08 21:14:18",
      "username": "dave",
      "id": "4c6b7705d6ea744abc000f23",
      "gender": "male",
      "phone": "4158065000",
      "last_name": "Morin",
      "is_friend": true,
      "first_name": "Dave",
      "email": "dave@davemorin.com"
    },
    "4ce241f0b3bf572b43000096": {
      "photo": {
        "ios": {
          "2x": {
            "height": 160,
            "file": "processed_160x160.jpg",
            "width": 160
          },
          "1x": {
            "height": 80,
            "file": "processed_80x80.jpg",
            "width": 80
          }
        },
        "url": "https://s3-us-west-1.amazonaws.com/images.path.com/profile_photos/ab908bed7650846dab7fc5af780646b56411b84d",
        "version": 3,
        "original": {
          "file": "original.jpg"
        }
      },
      "facebook_id": "13808625",
      "created_at": "2010-11-16 08:33:52",
      "username": "vanessa-schnei",
      "id": "4ce241f0b3bf572b43000096",
      "gender": "female",
      "phone": "7173831469",
      "last_name": "Schneider",
      "is_friend": true,
      "first_name": "Vanessa",
      "email": "vgschneider@gmail.com"
    },
    "4ce157547834d82432000211": {
      "photo": {
        "ios": {
          "2x": {
            "height": 160,
            "file": "processed_160x160.jpg",
            "width": 160
          },
          "1x": {
            "height": 80,
            "file": "processed_80x80.jpg",
            "width": 80
          }
        },
        "url": "https://s3-us-west-1.amazonaws.com/images.path.com/profile_photos/967e24face49fae5c2e92849c873dfa10d30af0d",
        "version": 3,
        "original": {
          "file": "original.jpg"
        }
      },
      "facebook_id": "500126071",
      "created_at": "2010-11-15 15:52:52",
      "username": "nathanfolkman",
      "id": "4ce157547834d82432000211",
      "gender": "male",
      "phone": "2129200631",
      "last_name": "Folkman",
      "first_name": "Nathan",
      "email": "nathan.folkman@gmail.com"
    }
  },
  "moments": [
    {
      "location": {
        "elevation": 23.1346111297607,
        "city": "Palo Alto",
        "country": "US",
        "accuracy": 10.0,
        "lng": -122.16152188216,
        "elevation_accuracy": 19.0,
        "county": "Santa Clara",
        "neighborhood": "Downtown North",
        "province": "CA",
        "lat": 37.446361902181
      },
      "data": {
        "id": "336195090"
      },
      "custom_id": "BD8E5253-D627-4A25-8617-BB1BFF14094F",
      "block_type": "chapter",
      "block_id": "4e4c6bde6a9eba13ed00004c",
      "id": "4e4c6ce26a9eba13ed000051",
      "user_id": "4ce157547834d82432000211",
      "type": "music",
      "state": "live",
      "created": 1313631456.54107
    },
    {
      "location": {
        "elevation": 22.2648315429688,
        "city": "Palo Alto",
        "country": "US",
        "accuracy": 10.0,
        "lng": -122.161552217476,
        "elevation_accuracy": 19.0,
        "county": "Santa Clara",
        "neighborhood": "Downtown North",
        "province": "CA",
        "lat": 37.4463779585157
      },
      "data": {
        "photo": {
          "ios": {
            "2x": {
              "height": 478,
              "file": "2x.jpg",
              "width": 640
            },
            "1x": {
              "height": 239,
              "file": "1x.jpg",
              "width": 320
            }
          },
          "url": "http://images.path.com.s3.amazonaws.com/619b9a46-5c42-42fa-8165-92a38c58b4d4",
          "original": {
            "height": "956",
            "file": "original.jpg",
            "width": "1280"
          }
        },
        "filter": "PTPolaroidFilter",
        "processed": true
      },
      "custom_id": "68584D14-BACD-4E4C-B97A-E496550836DB",
      "block_type": "chapter",
      "block_id": "4e4c6bde6a9eba13ed00004c",
      "id": "4e4c6c9e6a9eba13ed00004f",
      "user_id": "4ce157547834d82432000211",
      "type": "photo",
      "state": "live",
      "created": 1313631383.30309
    },
    {
      "location": {
        "elevation": 12.2276744842529,
        "city": "Palo Alto",
        "country": "US",
        "accuracy": 10.0,
        "lng": -122.161634741164,
        "elevation_accuracy": 19.0,
        "county": "Santa Clara",
        "neighborhood": "Downtown North",
        "province": "CA",
        "lat": 37.4462251520696
      },
      "data": {
        "id": "4b2af448f964a520cbb224e3"
      },
      "custom_id": "1A568C98-5A5E-47FD-850D-A10F71EF6D28",
      "block_type": "chapter",
      "block_id": "4e4c6bde6a9eba13ed00004c",
      "id": "4e4c6c156a9eba13ed00004e",
      "user_id": "4ce157547834d82432000211",
      "type": "place",
      "state": "live",
      "created": 1313631249.27809
    },
    {
      "location": {
        "elevation": 25.09326171875,
        "city": "Palo Alto",
        "country": "US",
        "accuracy": 30.0,
        "lng": -122.161408173181,
        "elevation_accuracy": 57.0,
        "county": "Santa Clara",
        "neighborhood": "Downtown North",
        "province": "CA",
        "lat": 37.4461653450141
      },
      "data": {
        "people": [
          {
            "id": "4ce241f0b3bf572b43000096",
            "type": "path"
          }
        ]
      },
      "custom_id": "13AC5B28-A663-4517-B17C-4E7857E1ABBD",
      "block_type": "chapter",
      "block_id": "4e4c6bde6a9eba13ed00004c",
      "id": "4e4c6bf66a9eba13ed00004d",
      "user_id": "4ce157547834d82432000211",
      "type": "people",
      "state": "live",
      "created": 1313631219.58389
    },
    {
      "location": {
        "elevation": 25.0464820861816,
        "city": "Palo Alto",
        "country": "US",
        "accuracy": 50.0,
        "lng": -122.161399213187,
        "elevation_accuracy": 95.0,
        "county": "Santa Clara",
        "neighborhood": "University South",
        "province": "CA",
        "lat": 37.446068755451
      },
      "data": {
        "foods": [
          {
            "category": "Pasta",
            "icon": "Pasta"
          }
        ]
      },
      "custom_id": "8273143C-CFA5-4D06-AEF4-9974CC247134",
      "block_type": "section",
      "block_id": "4e4c659b6a9eba13ed000034",
      "id": "4e4c6bc56a9eba13ed00004b",
      "user_id": "4ce157547834d82432000211",
      "type": "food",
      "state": "live",
      "created": 1313631170.56391
    },
    {
      "location": {
        "elevation": 22.7376403808594,
        "city": "Palo Alto",
        "country": "US",
        "accuracy": 65.0,
        "lng": -122.161175142664,
        "elevation_accuracy": 10.0,
        "county": "Santa Clara",
        "neighborhood": "Downtown North",
        "province": "CA",
        "lat": 37.446396402839
      },
      "data": {
        "id": "4b2af448f964a520cbb224e3"
      },
      "custom_id": "4C0956F6-67A9-46FD-BE6A-0BD70FA2FFF0",
      "comments": [
        {
          "body": "One of our go to places.",
          "id": "4e4c6a926a9eba13ed000049",
          "user_id": "4ce157547834d82432000211",
          "created": 1313630861.82579
        },
        {
          "body": "Nice. I miss that place.",
          "id": "4e4c6a5a6a9eba13ed000048",
          "user_id": "4c6b7705d6ea744abc000f23",
          "created": 1313630811.39573
        }
      ],
      "block_type": "section",
      "block_id": "4e4c659b6a9eba13ed000034",
      "id": "4e4c6a236a9eba13ed000047",
      "user_id": "4ce157547834d82432000211",
      "type": "place",
      "state": "live",
      "created": 1313630754.07169
    },
    {
      "location": {
        "elevation": 9.8900318145752,
        "city": "San Francisco",
        "country": "US",
        "accuracy": 30.0,
        "lng": -122.394814257021,
        "elevation_accuracy": 57.0,
        "county": "San Francisco",
        "neighborhood": "Mission Bay",
        "province": "CA",
        "lat": 37.7760695787736
      },
      "data": {
        "photo": {
          "ios": {
            "2x": {
              "height": 478,
              "file": "2x.jpg",
              "width": 640
            },
            "1x": {
              "height": 239,
              "file": "1x.jpg",
              "width": 320
            }
          },
          "url": "http://images.path.com.s3.amazonaws.com/5b33c258-35c0-4727-8956-09a113f9f790",
          "original": {
            "height": "956",
            "file": "original.jpg",
            "width": "1280"
          }
        },
        "filter": "PTBWOpenGLFilter",
        "processed": true
      },
      "custom_id": "3189FDB8-31E0-4D4C-BD6E-902B77929324",
      "block_type": "section",
      "block_id": "4e4c52d56a9eba13e7000007",
      "id": "4e4c5cbc6a9eba13ed00001c",
      "user_id": "4ce157547834d82432000211",
      "type": "photo",
      "state": "live",
      "created": 1313627314.17235
    },
    {
      "location": {
        "elevation": 9.4061107635498,
        "city": "San Francisco",
        "country": "US",
        "accuracy": 50.0,
        "lng": -122.3946159304,
        "elevation_accuracy": 95.0,
        "county": "San Francisco",
        "neighborhood": "Mission Bay",
        "province": "CA",
        "lat": 37.7763001278202
      },
      "data": {
        "people": [
          {
            "id": "4cc7581122645d0edd000026",
            "type": "path"
          }
        ]
      },
      "custom_id": "03023321-BB4E-4481-96A7-907D13D9EE77",
      "block_type": "section",
      "block_id": "4e4c52d56a9eba13e7000007",
      "id": "4e4c5b3c6a9eba13ed00001b",
      "user_id": "4ce157547834d82432000211",
      "type": "people",
      "state": "live",
      "created": 1313626938.1281
    },
    {
      "location": {
        "elevation": 11.8000240325928,
        "city": "San Francisco",
        "country": "US",
        "accuracy": 50.0,
        "lng": -122.394637560628,
        "elevation_accuracy": 95.0,
        "county": "San Francisco",
        "neighborhood": "Mission Bay",
        "province": "CA",
        "lat": 37.7765823445111
      },
      "data": {
        "id": "45073758f964a52021391fe3"
      },
      "custom_id": "BB932494-91B0-49B2-9222-F14E8D84FC29",
      "block_type": "section",
      "block_id": "4e4c52d56a9eba13e7000007",
      "id": "4e4c5b056a9eba13ed000018",
      "user_id": "4ce157547834d82432000211",
      "type": "place",
      "state": "live",
      "created": 1313626883.70605
    },
    {
      "location": {
        "elevation": 69.5850219726562,
        "city": "San Francisco",
        "country": "US",
        "accuracy": 50.0,
        "lng": -122.392838796642,
        "elevation_accuracy": 95.0,
        "county": "San Francisco",
        "neighborhood": "South Beach",
        "province": "CA",
        "lat": 37.7792625976479
      },
      "data": {
        "foods": [
          {
            "category": "Beer",
            "icon": "Beer"
          }
        ]
      },
      "custom_id": "71C970F2-6347-4A45-98C2-7C3E692D6FD0",
      "comments": [
        {
          "body": "I like beer ",
          "id": "4e4c5a026a9eba13ed000013",
          "user_id": "4ce157547834d82432000211",
          "created": 1313626621.39533
        }
      ],
      "block_type": "section",
      "block_id": "4e4c52d56a9eba13e7000007",
      "id": "4e4c59ef6a9eba13ed000012",
      "user_id": "4ce157547834d82432000211",
      "type": "food",
      "state": "live",
      "created": 1313626606.09577
    },
    {
      "location": {
        "elevation": 11.3236637115479,
        "city": "San Francisco",
        "country": "US",
        "accuracy": 10.0,
        "lng": -122.394146393128,
        "elevation_accuracy": 12.8792198412543,
        "county": "San Francisco",
        "neighborhood": "Financial District",
        "province": "CA",
        "lat": 37.7903437709008
      },
      "data": {
        "id": "432163690"
      },
      "custom_id": "21249950-6FF0-456B-BFC7-FC16679F0DB8",
      "block_type": "section",
      "block_id": "4e4c52d56a9eba13e7000007",
      "id": "4e4c53046a9eba13e7000009",
      "user_id": "4ce157547834d82432000211",
      "type": "music",
      "state": "live",
      "created": 1313624835.96247
    }
  ]
}
